{
    "description": "",
    "tags": [],
    "size": {
        "height": 1583,
        "width": 625
    },
    "objects": [
        {
            "id": 563554204,
            "classId": 2719717,
            "description": "",
            "geometryType": "polygon",
            "labelerLogin": "deguerrydeb",
            "createdAt": "2020-10-26T16:03:50.248Z",
            "updatedAt": "2020-10-26T16:04:12.507Z",
            "tags": [],
            "classTitle": "chordophone",
            "points": {
                "exterior": [
                    [
                        336,
                        1543
                    ],
                    [
                        259,
                        1541
                    ],
                    [
                        215,
                        1506
                    ],
                    [
                        179,
                        1463
                    ],
                    [
                        158,
                        1405
                    ],
                    [
                        157,
                        1329
                    ],
                    [
                        166,
                        1259
                    ],
                    [
                        181,
                        1194
                    ],
                    [
                        201,
                        1135
                    ],
                    [
                        213,
                        1069
                    ],
                    [
                        213,
                        992
                    ],
                    [
                        212,
                        914
                    ],
                    [
                        203,
                        844
                    ],
                    [
                        190,
                        778
                    ],
                    [
                        187,
                        708
                    ],
                    [
                        205,
                        646
                    ],
                    [
                        238,
                        601
                    ],
                    [
                        273,
                        557
                    ],
                    [
                        280,
                        485
                    ],
                    [
                        282,
                        408
                    ],
                    [
                        282,
                        331
                    ],
                    [
                        273,
                        261
                    ],
                    [
                        229,
                        240
                    ],
                    [
                        242,
                        174
                    ],
                    [
                        275,
                        128
                    ],
                    [
                        297,
                        70
                    ],
                    [
                        349,
                        83
                    ],
                    [
                        384,
                        127
                    ],
                    [
                        417,
                        173
                    ],
                    [
                        411,
                        232
                    ],
                    [
                        366,
                        265
                    ],
                    [
                        358,
                        337
                    ],
                    [
                        356,
                        414
                    ],
                    [
                        358,
                        491
                    ],
                    [
                        363,
                        565
                    ],
                    [
                        404,
                        603
                    ],
                    [
                        438,
                        648
                    ],
                    [
                        453,
                        712
                    ],
                    [
                        446,
                        784
                    ],
                    [
                        434,
                        850
                    ],
                    [
                        421,
                        917
                    ],
                    [
                        414,
                        989
                    ],
                    [
                        416,
                        1064
                    ],
                    [
                        427,
                        1132
                    ],
                    [
                        446,
                        1192
                    ],
                    [
                        462,
                        1255
                    ],
                    [
                        470,
                        1326
                    ],
                    [
                        471,
                        1398
                    ],
                    [
                        454,
                        1459
                    ],
                    [
                        418,
                        1503
                    ],
                    [
                        373,
                        1536
                    ]
                ],
                "interior": []
            }
        }
    ]
}