{
    "description": "",
    "tags": [],
    "size": {
        "height": 800,
        "width": 559
    },
    "objects": [
        {
            "id": 563550450,
            "classId": 2719717,
            "description": "",
            "geometryType": "polygon",
            "labelerLogin": "deguerrydeb",
            "createdAt": "2020-10-26T16:03:50.248Z",
            "updatedAt": "2020-10-26T16:04:12.507Z",
            "tags": [],
            "classTitle": "chordophone",
            "points": {
                "exterior": [
                    [
                        276,
                        756
                    ],
                    [
                        246,
                        749
                    ],
                    [
                        218,
                        740
                    ],
                    [
                        195,
                        726
                    ],
                    [
                        186,
                        698
                    ],
                    [
                        186,
                        661
                    ],
                    [
                        191,
                        629
                    ],
                    [
                        206,
                        607
                    ],
                    [
                        223,
                        586
                    ],
                    [
                        241,
                        567
                    ],
                    [
                        253,
                        542
                    ],
                    [
                        257,
                        509
                    ],
                    [
                        258,
                        474
                    ],
                    [
                        258,
                        437
                    ],
                    [
                        258,
                        400
                    ],
                    [
                        258,
                        363
                    ],
                    [
                        258,
                        326
                    ],
                    [
                        258,
                        289
                    ],
                    [
                        258,
                        252
                    ],
                    [
                        258,
                        215
                    ],
                    [
                        258,
                        178
                    ],
                    [
                        256,
                        143
                    ],
                    [
                        239,
                        143
                    ],
                    [
                        224,
                        125
                    ],
                    [
                        242,
                        111
                    ],
                    [
                        258,
                        95
                    ],
                    [
                        265,
                        65
                    ],
                    [
                        292,
                        58
                    ],
                    [
                        304,
                        83
                    ],
                    [
                        307,
                        111
                    ],
                    [
                        301,
                        142
                    ],
                    [
                        299,
                        177
                    ],
                    [
                        299,
                        214
                    ],
                    [
                        299,
                        251
                    ],
                    [
                        299,
                        288
                    ],
                    [
                        299,
                        325
                    ],
                    [
                        299,
                        362
                    ],
                    [
                        299,
                        399
                    ],
                    [
                        300,
                        435
                    ],
                    [
                        300,
                        472
                    ],
                    [
                        301,
                        507
                    ],
                    [
                        302,
                        542
                    ],
                    [
                        314,
                        567
                    ],
                    [
                        331,
                        587
                    ],
                    [
                        347,
                        608
                    ],
                    [
                        364,
                        628
                    ],
                    [
                        370,
                        659
                    ],
                    [
                        368,
                        694
                    ],
                    [
                        358,
                        721
                    ],
                    [
                        339,
                        738
                    ],
                    [
                        308,
                        744
                    ],
                    [
                        281,
                        754
                    ]
                ],
                "interior": []
            }
        }
    ]
}