{
    "description": "",
    "tags": [],
    "size": {
        "height": 3000,
        "width": 2001
    },
    "objects": [
        {
            "id": 563550078,
            "classId": 2719717,
            "description": "",
            "geometryType": "polygon",
            "labelerLogin": "deguerrydeb",
            "createdAt": "2020-10-26T16:03:50.248Z",
            "updatedAt": "2020-10-26T16:04:12.507Z",
            "tags": [],
            "classTitle": "chordophone",
            "points": {
                "exterior": [
                    [
                        1179,
                        2994
                    ],
                    [
                        1013,
                        2991
                    ],
                    [
                        895,
                        2940
                    ],
                    [
                        774,
                        2892
                    ],
                    [
                        697,
                        2800
                    ],
                    [
                        631,
                        2697
                    ],
                    [
                        612,
                        2547
                    ],
                    [
                        622,
                        2388
                    ],
                    [
                        664,
                        2261
                    ],
                    [
                        747,
                        2175
                    ],
                    [
                        790,
                        2049
                    ],
                    [
                        766,
                        1910
                    ],
                    [
                        718,
                        1789
                    ],
                    [
                        689,
                        1649
                    ],
                    [
                        686,
                        1489
                    ],
                    [
                        730,
                        1363
                    ],
                    [
                        808,
                        1272
                    ],
                    [
                        913,
                        1209
                    ],
                    [
                        943,
                        1070
                    ],
                    [
                        961,
                        919
                    ],
                    [
                        973,
                        762
                    ],
                    [
                        942,
                        624
                    ],
                    [
                        942,
                        479
                    ],
                    [
                        1012,
                        380
                    ],
                    [
                        1045,
                        244
                    ],
                    [
                        1122,
                        153
                    ],
                    [
                        1201,
                        243
                    ],
                    [
                        1269,
                        344
                    ],
                    [
                        1276,
                        462
                    ],
                    [
                        1196,
                        550
                    ],
                    [
                        1137,
                        660
                    ],
                    [
                        1114,
                        807
                    ],
                    [
                        1107,
                        968
                    ],
                    [
                        1105,
                        1128
                    ],
                    [
                        1164,
                        1238
                    ],
                    [
                        1304,
                        1267
                    ],
                    [
                        1401,
                        1339
                    ],
                    [
                        1468,
                        1441
                    ],
                    [
                        1473,
                        1603
                    ],
                    [
                        1462,
                        1761
                    ],
                    [
                        1413,
                        1880
                    ],
                    [
                        1378,
                        2015
                    ],
                    [
                        1407,
                        2149
                    ],
                    [
                        1479,
                        2246
                    ],
                    [
                        1535,
                        2359
                    ],
                    [
                        1554,
                        2509
                    ],
                    [
                        1551,
                        2665
                    ],
                    [
                        1516,
                        2799
                    ],
                    [
                        1442,
                        2893
                    ],
                    [
                        1348,
                        2968
                    ],
                    [
                        1204,
                        2993
                    ]
                ],
                "interior": []
            }
        }
    ]
}