{
    "description": "",
    "tags": [],
    "size": {
        "height": 800,
        "width": 382
    },
    "objects": [
        {
            "id": 563546279,
            "classId": 2719717,
            "description": "",
            "geometryType": "polygon",
            "labelerLogin": "deguerrydeb",
            "createdAt": "2020-10-26T16:03:50.248Z",
            "updatedAt": "2020-12-02T23:53:11.848Z",
            "tags": [],
            "classTitle": "chordophone",
            "points": {
                "exterior": [
                    [
                        164,
                        749
                    ],
                    [
                        126,
                        747
                    ],
                    [
                        91,
                        742
                    ],
                    [
                        69,
                        724
                    ],
                    [
                        65,
                        688
                    ],
                    [
                        72,
                        655
                    ],
                    [
                        76,
                        619
                    ],
                    [
                        76,
                        579
                    ],
                    [
                        75,
                        540
                    ],
                    [
                        76,
                        501
                    ],
                    [
                        76,
                        461
                    ],
                    [
                        75,
                        422
                    ],
                    [
                        75,
                        382
                    ],
                    [
                        74,
                        343
                    ],
                    [
                        72,
                        305
                    ],
                    [
                        66,
                        271
                    ],
                    [
                        65,
                        232
                    ],
                    [
                        65,
                        192
                    ],
                    [
                        64,
                        153
                    ],
                    [
                        64,
                        113
                    ],
                    [
                        65,
                        73
                    ],
                    [
                        66,
                        40
                    ],
                    [
                        93,
                        22
                    ],
                    [
                        127,
                        24
                    ],
                    [
                        168,
                        26
                    ],
                    [
                        217,
                        63
                    ],
                    [
                        243,
                        77
                    ],
                    [
                        265,
                        95
                    ],
                    [
                        289,
                        111
                    ],
                    [
                        316,
                        124
                    ],
                    [
                        343,
                        137
                    ],
                    [
                        367,
                        145
                    ],
                    [
                        365,
                        184
                    ],
                    [
                        375,
                        257
                    ],
                    [
                        350,
                        253
                    ],
                    [
                        336,
                        280
                    ],
                    [
                        327,
                        311
                    ],
                    [
                        317,
                        341
                    ],
                    [
                        307,
                        371
                    ],
                    [
                        300,
                        403
                    ],
                    [
                        290,
                        433
                    ],
                    [
                        280,
                        464
                    ],
                    [
                        271,
                        495
                    ],
                    [
                        261,
                        525
                    ],
                    [
                        251,
                        555
                    ],
                    [
                        243,
                        587
                    ],
                    [
                        235,
                        619
                    ],
                    [
                        226,
                        650
                    ],
                    [
                        217,
                        681
                    ],
                    [
                        206,
                        710
                    ],
                    [
                        192,
                        735
                    ],
                    [
                        165,
                        748
                    ]
                ],
                "interior": []
            }
        }
    ]
}