{
    "description": "",
    "tags": [],
    "size": {
        "height": 544,
        "width": 750
    },
    "objects": [
        {
            "id": 563551362,
            "classId": 2719717,
            "description": "",
            "geometryType": "polygon",
            "labelerLogin": "deguerrydeb",
            "createdAt": "2020-10-26T16:03:50.248Z",
            "updatedAt": "2020-10-26T16:04:12.507Z",
            "tags": [],
            "classTitle": "chordophone",
            "points": {
                "exterior": [
                    [
                        63,
                        440
                    ],
                    [
                        52,
                        419
                    ],
                    [
                        71,
                        403
                    ],
                    [
                        90,
                        389
                    ],
                    [
                        111,
                        376
                    ],
                    [
                        130,
                        361
                    ],
                    [
                        153,
                        349
                    ],
                    [
                        176,
                        338
                    ],
                    [
                        199,
                        328
                    ],
                    [
                        224,
                        318
                    ],
                    [
                        248,
                        308
                    ],
                    [
                        272,
                        298
                    ],
                    [
                        296,
                        289
                    ],
                    [
                        321,
                        279
                    ],
                    [
                        345,
                        270
                    ],
                    [
                        370,
                        260
                    ],
                    [
                        394,
                        251
                    ],
                    [
                        418,
                        240
                    ],
                    [
                        443,
                        231
                    ],
                    [
                        469,
                        223
                    ],
                    [
                        495,
                        215
                    ],
                    [
                        524,
                        210
                    ],
                    [
                        555,
                        207
                    ],
                    [
                        588,
                        206
                    ],
                    [
                        620,
                        208
                    ],
                    [
                        653,
                        209
                    ],
                    [
                        684,
                        212
                    ],
                    [
                        683,
                        234
                    ],
                    [
                        653,
                        239
                    ],
                    [
                        622,
                        241
                    ],
                    [
                        591,
                        245
                    ],
                    [
                        563,
                        250
                    ],
                    [
                        538,
                        259
                    ],
                    [
                        512,
                        268
                    ],
                    [
                        484,
                        273
                    ],
                    [
                        455,
                        278
                    ],
                    [
                        427,
                        284
                    ],
                    [
                        401,
                        292
                    ],
                    [
                        376,
                        301
                    ],
                    [
                        352,
                        311
                    ],
                    [
                        329,
                        322
                    ],
                    [
                        306,
                        333
                    ],
                    [
                        282,
                        344
                    ],
                    [
                        259,
                        355
                    ],
                    [
                        236,
                        366
                    ],
                    [
                        213,
                        376
                    ],
                    [
                        190,
                        387
                    ],
                    [
                        165,
                        397
                    ],
                    [
                        142,
                        407
                    ],
                    [
                        119,
                        418
                    ],
                    [
                        96,
                        430
                    ],
                    [
                        71,
                        438
                    ]
                ],
                "interior": []
            }
        }
    ]
}